poetry_demo_xxxxyy/__init__.py
poetry_demo_xxxxyy/main.py
poetry_demo_xxxxyy-0.1.0.dist-info/WHEEL
poetry_demo_xxxxyy-0.1.0.dist-info/METADATA
poetry_demo_xxxxyy-0.1.0.dist-info/RECORD
