Metadata-Version: 2.1
Name: poetry-demo-xxxxyy
Version: 0.1.0
Summary: 
Author: Snow Shen
Author-email: snowshen@tagtoo.com
Requires-Python: >=3.8,<4.0
Classifier: Programming Language :: Python :: 3
Classifier: Programming Language :: Python :: 3.8
Requires-Dist: pendulum (>=2.1.2,<3.0.0)
